hvad/__init__.py
hvad/admin.py
hvad/descriptors.py
hvad/exceptions.py
hvad/fields.py
hvad/forms.py
hvad/manager.py
hvad/models.py
hvad/query.py
hvad/settings.py
hvad/utils.py
hvad/views.py
hvad/contrib/__init__.py
hvad/contrib/migration/__init__.py
hvad/contrib/migration/hvad_migration.py
hvad/contrib/restframework/__init__.py
hvad/contrib/restframework/serializers.py
hvad/contrib/restframework/utils.py
hvad/locale/en/LC_MESSAGES/django.mo
hvad/locale/en/LC_MESSAGES/django.po
hvad/locale/fr/LC_MESSAGES/django.mo
hvad/locale/fr/LC_MESSAGES/django.po
hvad/locale/it/LC_MESSAGES/django.mo
hvad/locale/it/LC_MESSAGES/django.po
hvad/locale/lv/LC_MESSAGES/django.mo
hvad/locale/lv/LC_MESSAGES/django.po
hvad/locale/ru/LC_MESSAGES/django.mo
hvad/locale/ru/LC_MESSAGES/django.po
hvad/templates/admin/hvad/change_form.html
hvad/templates/admin/hvad/deletion_not_allowed.html
hvad/templates/admin/hvad/edit_inline/stacked.html
hvad/templates/admin/hvad/edit_inline/tabular.html
hvad/templates/admin/hvad/includes/translation_tabs.html
hvad/test_utils/__init__.py
hvad/test_utils/context_managers.py
hvad/test_utils/data.py
hvad/test_utils/fixtures.py
hvad/test_utils/forms.py
hvad/test_utils/testcase.py
hvad/test_utils/project/__init__.py
hvad/test_utils/project/manage.py
hvad/test_utils/project/urls.py
hvad/test_utils/project/app/__init__.py
hvad/test_utils/project/app/admin.py
hvad/test_utils/project/app/models.py
hvad/tests/__init__.py
hvad/tests/abstract.py
hvad/tests/admin.py
hvad/tests/basic.py
hvad/tests/dates.py
hvad/tests/docs.py
hvad/tests/forms.py
hvad/tests/forms_inline.py
hvad/tests/limit_choices_to.py
hvad/tests/ordering.py
hvad/tests/proxy.py
hvad/tests/query.py
hvad/tests/queryset_override.py
hvad/tests/related.py
hvad/tests/serialization.py
hvad/tests/utils.py
hvad/tests/views.py
hvad/tests/contrib/__init__.py
hvad/tests/contrib/restframework.py
lotrek_django_hvad-2.0.7.dist-info/AUTHORS
lotrek_django_hvad-2.0.7.dist-info/LICENSE
lotrek_django_hvad-2.0.7.dist-info/METADATA
lotrek_django_hvad-2.0.7.dist-info/WHEEL
lotrek_django_hvad-2.0.7.dist-info/top_level.txt
lotrek_django_hvad-2.0.7.dist-info/RECORD
