Metadata-Version: 2.1
Name: lotrek-django-hvad
Version: 2.0.7
Summary: A content translation framework for django integrated automatically in the normal ORM. Removes the pain of having to think about translations in a django project.
Home-page: https://github.com/lotrekagency/django-hvad
Author: Lotrèk
Author-email: dimmitutto@lotrek.it
License: MIT
Keywords: cms,django,api cms
Classifier: Development Status :: 5 - Production/Stable
Classifier: Framework :: Django
Classifier: Intended Audience :: Developers
Classifier: License :: OSI Approved :: BSD License
Classifier: Operating System :: OS Independent
Classifier: Programming Language :: Python :: 2.7
Classifier: Programming Language :: Python :: 3.4
Classifier: Programming Language :: Python :: 3.5
Classifier: Programming Language :: Python :: 3.6
Classifier: Topic :: Database
Classifier: Topic :: Internet :: WWW/HTTP :: Dynamic Content
Classifier: Topic :: Text Processing :: Linguistic
Requires-Python: >=3.0.*
License-File: LICENSE
License-File: AUTHORS
Requires-Dist: Django (>=1.8)
